drf_nested_multipart/__init__.py
drf_nested_multipart/renderers.py
drf_nested_multipart/__pycache__/__init__.cpython-38.pyc
drf_nested_multipart/__pycache__/renderers.cpython-38.pyc
drf_nested_multipart/utils/encoders.py
drf_nested_multipart/utils/__pycache__/encoders.cpython-38.pyc
nested_multipart_renderer-0.2.0.dist-info/LICENSE
nested_multipart_renderer-0.2.0.dist-info/METADATA
nested_multipart_renderer-0.2.0.dist-info/WHEEL
nested_multipart_renderer-0.2.0.dist-info/top_level.txt
nested_multipart_renderer-0.2.0.dist-info/RECORD
